geng/__init__.py
geng-0.0.1.dist-info/DESCRIPTION.rst
geng-0.0.1.dist-info/METADATA
geng-0.0.1.dist-info/RECORD
geng-0.0.1.dist-info/WHEEL
geng-0.0.1.dist-info/entry_points.txt
geng-0.0.1.dist-info/metadata.json
geng-0.0.1.dist-info/top_level.txt
